FullAdder/full_adder.v
module Full_Adder_df(sum,c_out,a,b,c_in);
output sum,c_out;
input a,b,c_in;

assign sum = a^b^c_in;
assign c_out = (a & b) | (c_in&(a^b));
endmodule

module Full_Adder_bh(sum,c_out,a,b,c_in);
output reg sum,c_out;
input a,b,c_in;
always @(*) begin
    sum = a^b^c_in;
    c_out = (a&b) | (c_in&(a^b));
end
endmodule

module Full_Adder_gl(sum,c_out,a,b,c_in);
 output sum,c_out;
input a,b,c_in;
wire w1,w2,w3;

xor u1(w1,a,b);
xor u2(sum,w1,c_in);

and u3(w2,w1,c_in);
and u4(w3,a,b);
or u5(c_out,w2,w3);

endmodule

FullAdder/Full_adder_tb.v
`timescale 1ps/1ps
`include "full_adder.v"

module Full_adder_tb();

wire sum, c_out;
reg a,b,c_in;

Full_Adder_df mut(.sum(sum),.c_out(c_out),.a(a),.b(b),.c_in(c_in));
initial begin
    $display("Full adder demonstration");
    $monitor("time: %0t | a:%0b | b:%0b | c_in: %0b | sum : %0b | c_out : %0b",$time,a,b,c_in,sum,c_out);
    #5
    a=0; b=0; c_in=0;
    #5
    a=0; b=0; c_in=1;
    #5
    a=0; b=1; c_in=0;
    #5
    a=0; b=1; c_in=1;
    #5
    a=1; b=0; c_in=0;
    #5
    a=1; b=0; c_in=1;
    #5
    a=1; b=1; c_in=0;
    #5
    a=1; b=1; c_in=1;
    #5
    a=1; b=1'bx; c_in=1'bx;
    #5
    a=0; b=1'bx; c_in=0;
    #5
    $finish;

end

initial begin
    $dumpfile("full_adder.vcd");
    $dumpvars(0,Full_adder_tb);
end
endmodule

FullAdder/full_adder.vcd
$date
	Sat Mar 14 16:53:10 2026
$end
$version
	Icarus Verilog
$end
$timescale
	1ps
$end
$scope module Full_adder_tb $end
$var wire 1 ! sum $end
$var wire 1 " c_out $end
$var reg 1 # a $end
$var reg 1 $ b $end
$var reg 1 % c_in $end
$scope module mut $end
$var wire 1 # a $end
$var wire 1 $ b $end
$var wire 1 % c_in $end
$var wire 1 " c_out $end
$var wire 1 ! sum $end
$upscope $end
$upscope $end
$enddefinitions $end
$comment Show the parameter values. $end
$dumpall
$end
#0
$dumpvars
x%
x$
x#
x"
x!
$end
#5
0"
0!
0%
0$
0#
#10
1!
1%
#15
0%
1$
#20
1"
0!
1%
#25
0"
1!
0%
0$
1#
#30
1"
0!
1%
#35
0%
1$
#40
1!
1%
#45
x"
x!
x%
x$
#50
0"
0%
0#
