Delays/gate_delays.v
module D (out, a, b, c);
output out;
input a, b, c;
wire e;
and #(5) a1(e, a, b); // Delay of 5
or #(4) o1(out, e, c); // Delay of 4
endmodule

Delays/gate_delays_tb.v
`timescale 1ns/1ns
`include "gate_delays.v"

 module gate_delays_tb;

 reg A, B, C;
 wire OUT;
 D d1 (OUT, A, B, C);

 initial begin
 $dumpfile("gate_delays.vcd");
 $dumpvars(0,gate_delays_tb);
 A = 1'b0; B = 1'b0; C = 1'b0;
 #10 A = 1'b1; B = 1'b1; C = 1'b1;
 #10 A = 1'b1; B = 1'b0; C = 1'b0;
 #20 $finish;

 end

endmodule

Delays/gate_delays.vcd
$date
	Thu Mar 19 18:58:20 2026
$end
$version
	Icarus Verilog
$end
$timescale
	1ns
$end
$scope module gate_delays_tb $end
$var wire 1 ! OUT $end
$var reg 1 " A $end
$var reg 1 # B $end
$var reg 1 $ C $end
$scope module d1 $end
$var wire 1 " a $end
$var wire 1 # b $end
$var wire 1 $ c $end
$var wire 1 % e $end
$var wire 1 ! out $end
$upscope $end
$upscope $end
$enddefinitions $end
$comment Show the parameter values. $end
$dumpall
$end
#0
$dumpvars
x%
0$
0#
0"
x!
$end
#5
0%
#9
0!
#10
1$
1#
1"
#14
1!
#15
1%
#20
0$
0#
#25
0%
#29
0!
