FlipFlop/T_flipflop/t_flipflop.v
module t_flipflop_df(q,qbar,t,clk);
output  q,qbar;
input t,clk;

assign qbar= ~((qbar & t & clk) | q);
assign q = ~((q & t & clk) | qbar);
endmodule;

module t_flipflop_bh(q, qbar, t, clk,reset);
 output reg q;
 output qbar;
 input t, clk,reset;
assign qbar = ~q;//assign with wire 

initial 
q =0;
 always @(posedge clk) 
 begin
    case({t,reset})
    2'b00: q=q;
    2'b10: q=~q;
    2'b11: q=0;
    2'b01: q=0;
    endcase
 end
endmodule

module t_flipflop_gate(q,qbar,t,clk);
output q;
output qbar;
input t;
input clk;


wire w1,w2;

and u1(w1,qbar,t,clk);
nor u2(qbar,w1,q);
and u3(w2,q,t,clk);
nor u4(q,w2,qbar);
endmodule

Counter/3Bit_ripple_up_counter/3bitCounter.v

`include "../../FlipFlop/T_flipflop/t_flipflop.v"
module up_counter(q,t,clk , reset);
output [2:0] q;//array
// reg vec [3:0] ; //vector of 4 bit 
// reg [3:0] arr [4:0] ; //array of four element and each contain vector of 5 bit

wire [2:0] qbar;
input t,clk,reset;

  t_flipflop_bh t1(q[0],qbar[0],t,clk ,reset);
   t_flipflop_bh t2(q[1],qbar[1],t,qbar[0],reset);
   t_flipflop_bh t3(q[2],qbar[2],t,qbar[1],reset);
endmodule

Clock/clock_demo.v
`timescale 1ps/1ps

module my_clock(clk);
output clk;
reg c=1'b0;

always #5 c=~c;

assign clk = c;

endmodule

Reset/reset.v
module my_reset(reset);
output reset;
reg c=1'b0;
    initial begin
        #20
    c =1'b1;
    #5
    c=1'b0;
    #40
    c =1'b1;
    #5
    c=1'b0;
end

assign reset = c ;
endmodule

Counter/3Bit_ripple_up_counter/3bitCounter_tb.v
`timescale 1ps/1ps
`include "../../Clock/clock_demo.v"
`include "3bitCounter.v"
`include "../../Reset/reset.v"

module CounterUp3_tb();

wire [2:0]q;
reg t ; 
wire clk,reset;
initial t =1;
my_reset rut(reset);
my_clock cut(clk);
up_counter mut(.t(t),.q(q),.reset(reset),.clk(clk));
initial begin

$display("3 bit ripple postive asynchronous up counter demostration :");
$monitor("$time: %0t | clk : %0b | reset : %0b | t: %0b |  q2: %0b |q1: %0b | q0: %0b",$time,clk, reset,t,q[2],q[1],q[0]);
#100
$finish;
end
initial begin
    $dumpfile("3bitCounter.vcd");
    $dumpvars(0,CounterUp3_tb);
end
endmodule

Counter/3Bit_ripple_up_counter/3bitCounter.vcd
$date
	Sun Mar 15 20:01:09 2026
$end
$version
	Icarus Verilog
$end
$timescale
	1ps
$end
$scope module CounterUp3_tb $end
$var wire 1 ! reset $end
$var wire 3 " q [2:0] $end
$var wire 1 # clk $end
$var reg 1 $ t $end
$scope module cut $end
$var wire 1 # clk $end
$var reg 1 % c $end
$upscope $end
$scope module mut $end
$var wire 1 # clk $end
$var wire 1 $ t $end
$var wire 1 ! reset $end
$var wire 3 & qbar [2:0] $end
$var wire 3 ' q [2:0] $end
$scope module t1 $end
$var wire 1 # clk $end
$var wire 1 ( qbar $end
$var wire 1 $ t $end
$var wire 1 ! reset $end
$var reg 1 ) q $end
$upscope $end
$scope module t2 $end
$var wire 1 * clk $end
$var wire 1 + qbar $end
$var wire 1 $ t $end
$var wire 1 ! reset $end
$var reg 1 , q $end
$upscope $end
$scope module t3 $end
$var wire 1 - clk $end
$var wire 1 . qbar $end
$var wire 1 $ t $end
$var wire 1 ! reset $end
$var reg 1 / q $end
$upscope $end
$upscope $end
$scope module rut $end
$var wire 1 ! reset $end
$var reg 1 0 c $end
$upscope $end
$upscope $end
$enddefinitions $end
$comment Show the parameter values. $end
$dumpall
$end
#0
$dumpvars
00
1/
0.
0-
1,
0+
1*
0)
1(
b110 '
b1 &
0%
1$
0#
b110 "
0!
$end
#5
0*
b0 &
0(
b111 "
b111 '
1)
1#
1%
#10
0#
0%
#15
1.
0/
1-
1+
0,
1*
b111 &
1(
b0 "
b0 '
0)
1#
1%
#20
0#
0%
1!
10
#25
1#
1%
#30
0#
0%
#35
1#
1%
#40
0#
0%
#45
1#
1%
#50
0#
0%
#55
1#
1%
#60
0#
0%
0!
00
#65
1#
1%
1!
10
#70
0#
0%
0!
00
#75
0*
b110 &
0(
b1 "
b1 '
1)
1#
1%
#80
0#
0%
#85
0-
0+
1,
1*
b101 &
1(
b10 "
b10 '
0)
1#
1%
#90
0#
0%
#95
0*
b100 &
0(
b11 "
b11 '
1)
1#
1%
#100
0#
0%
