FlipFlop/JK_FlipFlop/jk_flipflop.v
module jk_flipflop_df(q,qbar,j,k,clk);
output  q,qbar;
input j,k,clk;

assign qbar= ~((qbar & j & clk) | q);
assign q = ~((q & k & clk) | qbar);
endmodule;

module jk_flipflop_bh(q, qbar, j, k, clk);
 output reg q;
 output qbar;
 input j, k, clk;
assign qbar = ~q;//assign with wire 
 always @(posedge clk) 
 begin
    case({j,k})
    2'b00: q = q;
    2'b01: q = 0;
    2'b10: q = 1;
    2'b11: q =~q; 
    endcase
 end
endmodule

module jk_flipflop_gate(q,qbar,j,k,clk);
output q;
output qbar;
input j,k;
input clk;


wire w1,w2;

and u1(w1,qbar,j,clk);
nor u2(qbar,w1,q);
and u3(w2,q,k,clk);
nor u4(q,w2,qbar);
endmodule

Clock/clock_demo.v
`timescale 1ps/1ps

module my_clock(clk);
output clk;
reg c=1'b0;

always #5 c=~c;

assign clk = c;

endmodule

FlipFlop/JK_FlipFlop/jk_flipflop_tb.v
`timescale 1ps/1ps
`include "jk_flipflop.v"
`include "../../Clock/clock_demo.v"


module jk_flipflop_tb();

wire q, qbar;
reg j,k;
wire clk;

my_clock mutt(clk);
jk_flipflop_bh mut(.q(q),.qbar(qbar),.j(j),.k(k),.clk(clk));

initial begin

$display("jk flipflop demostration :");
$monitor("$time: %0t | clk : %0b | j: %0b | k: %0b | q: %0b | qbar: %0b",$time,clk,j,k,q,qbar);
#5
j=0; k=0;
#10
j=0; k=1;
#10
j=1; k=0;
#10
j=1; k=1;
#10

$finish;

   
end

initial begin
    $dumpfile("jk_flipflop.vcd");
    $dumpvars(0,jk_flipflop_tb);
end
endmodule

FlipFlop/JK_FlipFlop/jk_flipflop.vcd
$date
	Sun Mar 15 16:42:32 2026
$end
$version
	Icarus Verilog
$end
$timescale
	1ps
$end
$scope module jk_flipflop_tb $end
$var wire 1 ! qbar $end
$var wire 1 " q $end
$var wire 1 # clk $end
$var reg 1 $ j $end
$var reg 1 % k $end
$scope module mut $end
$var wire 1 $ j $end
$var wire 1 % k $end
$var wire 1 ! qbar $end
$var wire 1 # clk $end
$var reg 1 " q $end
$upscope $end
$scope module mutt $end
$var wire 1 # clk $end
$var reg 1 & c $end
$upscope $end
$upscope $end
$enddefinitions $end
$comment Show the parameter values. $end
$dumpall
$end
#0
$dumpvars
0&
x%
x$
0#
x"
x!
$end
#5
0%
0$
1#
1&
#10
0#
0&
#15
1!
0"
1#
1&
1%
#20
0#
0&
#25
0!
1"
1#
1&
0%
1$
#30
0#
0&
#35
1!
0"
1#
1&
1%
#40
0#
0&
#45
0!
1"
1#
1&
