Subtracter/full_sub/full_sub.v
module full_subtracter_df(output diff, output b_out, input a,b,b_in);

assign diff = a^b^b_in;
assign b_out=~a&(b^b_in)|(b&b_in);

endmodule

module full_subtracter_bh(output reg diff, output reg b_out, input a,b,b_in);

always @(*)
begin
  diff = a^b^b_in;
 b_out=~a&(b^b_in)|(b&b_in);  
end


endmodule

module full_subtracter_gate(output diff, output b_out, input a,b,b_in);
wire w1,w2,w3;
xor(w1,b,b_in);
xor(diff,w1,a);
not(w2,a);
and(w2,w1);
and(w3,b,b_in);
or(w2,w3);
endmodule

Subtracter/full_sub/full_sub_tb.v
`timescale 1ps/1ps
`include "full_sub.v"

module full_subtracter_tb();
wire diff;
wire b_out;
reg a,b,b_in;
full_subtracter_df mut(.diff(diff),.b_out(b_out),.a(a),.b(b),.b_in(b_in));
// full_subtracter_bh mut(.diff(diff),.b_out(b_out),.a(a),.b(b),.b_in(b_in));
// full_subtracter_gate mut(.diff(diff),.b_out(b_out),.a(a),.b(b),.b_in(b_in));

initial begin
    $dumpfile("full_subtracter.vcd");
    $dumpvars(0,full_subtracter_tb);

    $display("full subtracter demonstration");
    $display("$time\t| a\t| b\t| b_in\t| diff\t| b_out\t");
    $monitor("%0t\t| %0b\t| %0b\t| %0b\t| %0b\t| %0b\t",$time,a,b,b_in,diff,b_out);
  #5
    a=0; b=0; b_in=0;
    #5
    a=0; b=0; b_in=1;
    #5
    a=0; b=1; b_in=0;
    #5
    a=0; b=1; b_in=1;
    #5
    a=1; b=0; b_in=0;
    #5
    a=1; b=0; b_in=1;
    #5
    a=1; b=1; b_in=0;
    #5
    a=1; b=1; b_in=1;
    #5
   
    $finish;
end
endmodule

Subtracter/full_sub/full_subtracter.vcd
$date
	Tue Mar 24 20:51:14 2026
$end
$version
	Icarus Verilog
$end
$timescale
	1ps
$end
$scope module full_subtracter_tb $end
$var wire 1 ! diff $end
$var wire 1 " b_out $end
$var reg 1 # a $end
$var reg 1 $ b $end
$var reg 1 % b_in $end
$scope module mut $end
$var wire 1 # a $end
$var wire 1 $ b $end
$var wire 1 % b_in $end
$var wire 1 " b_out $end
$var wire 1 ! diff $end
$upscope $end
$upscope $end
$enddefinitions $end
$comment Show the parameter values. $end
$dumpall
$end
#0
$dumpvars
x%
x$
x#
x"
x!
$end
#5
0"
0!
0%
0$
0#
#10
1"
1!
1%
#15
0%
1$
#20
0!
1%
#25
0"
1!
0%
0$
1#
#30
0!
1%
#35
0%
1$
#40
1"
1!
1%
