FlipFlop/SR_Flip_flop/sr_flipflop.v
module sr_flipflop_df(q,qbar,s,r,clk);
output q,qbar;
input s,r,clk;
reg w1,w2;

assign qbar = ~((s&clk) | q);
assign q = ~((r & clk) | qbar);
endmodule

module sr_flip_flop_bh(q,qbar,s,r,clk);
output reg q;
output qbar;
input s,r,clk;

assign qbar = ~q;

always @(posedge clk )
begin
    case({s,r})
    2'b11: q=1'bx;
    2'b10: q=1;
    2'b01: q=0;
    endcase
end
endmodule
module sr_flipflop_gate(q,qbar,s,r,clk);
output q,qbar;
input s,r,clk;
wire w1,w2;

and u1 (w1,s,clk);
nor u2(qbar,w1,q);
and u3(w2,r,clk);
nor u4(q,w2,qbar);

endmodule

Clock/clock_demo.v
`timescale 1ps/1ps

module my_clock(clk);
output clk;
reg c=1'b0;

always #5 c=~c;

assign clk = c;

endmodule

FlipFlop/SR_Flip_flop/sr_flipflop_tb.v
`timescale 1ps/1ps
`include "sr_flipflop.v"
`include "../../Clock/clock_demo.v"

module sr_flipflop_tb();
wire q,qbar ;
reg s,r;
wire clk;

// reg c=1'b0;

// wire clk ;
// always #5 c=~c;

// assign clk = c;
my_clock mutt(clk);
sr_flip_flop_bh mut(.q(q),.qbar(qbar),.s(s),.r(r),.clk(clk));

initial begin

$display("nor_latch demostration :");
$monitor("$time: %0t | clk : %0b | s: %0b | r: %0b | q: %0b | qbar: %0b",$time,clk,s,r,q,qbar);
#5
s=0; r=0;
#10
s=0; r=1;
#10
s=1; r=0;
#10
s=1; r=1;
#10

$finish;

   
end

initial begin
    $dumpfile("sr_flipflop.vcd");
    $dumpvars(0,sr_flipflop_tb);
end





endmodule

FlipFlop/SR_Flip_flop/sr_flipflop.vcd
$date
	Sat Mar 14 23:04:25 2026
$end
$version
	Icarus Verilog
$end
$timescale
	1ps
$end
$scope module sr_flipflop_tb $end
$var wire 1 ! qbar $end
$var wire 1 " q $end
$var wire 1 # clk $end
$var reg 1 $ r $end
$var reg 1 % s $end
$scope module mut $end
$var wire 1 ! qbar $end
$var wire 1 $ r $end
$var wire 1 % s $end
$var wire 1 # clk $end
$var reg 1 " q $end
$upscope $end
$scope module mutt $end
$var wire 1 # clk $end
$var reg 1 & c $end
$upscope $end
$upscope $end
$enddefinitions $end
$comment Show the parameter values. $end
$dumpall
$end
#0
$dumpvars
0&
x%
x$
0#
x"
x!
$end
#5
0$
0%
1#
1&
#10
0#
0&
#15
1!
0"
1#
1&
1$
#20
0#
0&
#25
0!
1"
1#
1&
0$
1%
#30
0#
0&
#35
x!
x"
1#
1&
1$
#40
0#
0&
#45
1#
1&
