Clock/clock_demo.v
`timescale 1ps/1ps

module my_clock(clk);
output clk;
reg c=1'b0;

always #5 c=~c;

assign clk = c;

endmodule

Clock/clock_demo_tb.v
`timescale 1ps/1ps
`include "clock_demo.v"

module clock_demo_tb();
output clk;
my_clock mut(clk);

initial begin
   #100
$finish; 
end
 
 initial begin
    $dumpfile("clock_demo.vcd");
    $dumpvars(0,clock_demo_tb);
 end
endmodule

Clock/clock_demo.vcd
$date
	Sat Mar 14 20:16:08 2026
$end
$version
	Icarus Verilog
$end
$timescale
	1ps
$end
$scope module clock_demo_tb $end
$var wire 1 ! clk $end
$scope module mut $end
$var wire 1 ! clk $end
$var reg 1 " c $end
$upscope $end
$upscope $end
$enddefinitions $end
$comment Show the parameter values. $end
$dumpall
$end
#0
$dumpvars
0"
0!
$end
#5
1!
1"
#10
0!
0"
#15
1!
1"
#20
0!
0"
#25
1!
1"
#30
0!
0"
#35
1!
1"
#40
0!
0"
#45
1!
1"
#50
0!
0"
#55
1!
1"
#60
0!
0"
#65
1!
1"
#70
0!
0"
#75
1!
1"
#80
0!
0"
#85
1!
1"
#90
0!
0"
#95
1!
1"
#100
0!
0"
